Orange3_Network-1.10.2-py3.13-nspkg.pth
orange3_network-1.10.2.dist-info/RECORD
orange3_network-1.10.2.dist-info/namespace_packages.txt
orange3_network-1.10.2.dist-info/WHEEL
orange3_network-1.10.2.dist-info/entry_points.txt
orange3_network-1.10.2.dist-info/top_level.txt
orange3_network-1.10.2.dist-info/METADATA
orange3_network-1.10.2.dist-info/licenses/LICENSE
orange3_network-1.10.2.dist-info/licenses/COPYING
orange3_network-1.10.2.data/data/help/orange3-network/index.html
orange3_network-1.10.2.data/data/help/orange3-network/searchindex.js
orange3_network-1.10.2.data/data/help/orange3-network/.buildinfo
orange3_network-1.10.2.data/data/help/orange3-network/genindex.html
orange3_network-1.10.2.data/data/help/orange3-network/search.html
orange3_network-1.10.2.data/data/help/orange3-network/objects.inv
orange3_network-1.10.2.data/data/help/orange3-network/_sources/index.rst.txt
orange3_network-1.10.2.data/data/help/orange3-network/_sources/widgets/networkofgroups.md.txt
orange3_network-1.10.2.data/data/help/orange3-network/_sources/widgets/networkexplorer.md.txt
orange3_network-1.10.2.data/data/help/orange3-network/_sources/widgets/networkfromdistances.md.txt
orange3_network-1.10.2.data/data/help/orange3-network/_sources/widgets/networkgenerator.md.txt
orange3_network-1.10.2.data/data/help/orange3-network/_sources/widgets/networkclustering.md.txt
orange3_network-1.10.2.data/data/help/orange3-network/_sources/widgets/singlemode.md.txt
orange3_network-1.10.2.data/data/help/orange3-network/_sources/widgets/networkfile.md.txt
orange3_network-1.10.2.data/data/help/orange3-network/_sources/widgets/networkanalysis.md.txt
orange3_network-1.10.2.data/data/help/orange3-network/_static/plus.png
orange3_network-1.10.2.data/data/help/orange3-network/_static/sphinx_highlight.js
orange3_network-1.10.2.data/data/help/orange3-network/_static/documentation_options.js
orange3_network-1.10.2.data/data/help/orange3-network/_static/searchtools.js
orange3_network-1.10.2.data/data/help/orange3-network/_static/file.png
orange3_network-1.10.2.data/data/help/orange3-network/_static/_sphinx_javascript_frameworks_compat.js
orange3_network-1.10.2.data/data/help/orange3-network/_static/custom.css
orange3_network-1.10.2.data/data/help/orange3-network/_static/language_data.js
