Metadata-Version: 2.4
Name: Orange3-Network
Version: 1.10.2
Summary: Networks add-on for Orange 3 data mining software package.
Home-page: https://github.com/biolab/orange3-network
Author: Laboratory of Bioinformatics, FRI UL
Author-email: info@biolab.si
License: GPLv3
Keywords: network,network analysis,network layout,network visualization,data mining,machine learning,artificial intelligence,orange,orange3 add-on
Classifier: Development Status :: 4 - Beta
Classifier: Environment :: X11 Applications :: Qt
Classifier: Environment :: Console
Classifier: Environment :: Plugins
Classifier: Programming Language :: Python
Classifier: License :: OSI Approved :: GNU General Public License v3 or later (GPLv3+)
Classifier: Operating System :: OS Independent
Classifier: Topic :: Scientific/Engineering :: Artificial Intelligence
Classifier: Topic :: Scientific/Engineering :: Visualization
Classifier: Topic :: Software Development :: Libraries :: Python Modules
Classifier: Intended Audience :: Education
Classifier: Intended Audience :: Science/Research
Classifier: Intended Audience :: Developers
Requires-Python: >=3.8
License-File: LICENSE
License-File: COPYING
Requires-Dist: anyqt
Requires-Dist: gensim
Requires-Dist: Orange3>=3.38.1
Requires-Dist: orange-widget-base
Requires-Dist: pyqtgraph
Requires-Dist: scipy
Requires-Dist: scikit-learn
Provides-Extra: gui
Requires-Dist: AnyQt; extra == "gui"
Provides-Extra: rest
Requires-Dist: numpydoc; extra == "rest"
Provides-Extra: test
Requires-Dist: coverage; extra == "test"
Provides-Extra: doc
Requires-Dist: sphinx; extra == "doc"
Requires-Dist: recommonmark; extra == "doc"
Requires-Dist: sphinx_rtd_theme; extra == "doc"
Dynamic: author
Dynamic: author-email
Dynamic: classifier
Dynamic: description
Dynamic: description-content-type
Dynamic: home-page
Dynamic: keywords
Dynamic: license
Dynamic: license-file
Dynamic: provides-extra
Dynamic: requires-dist
Dynamic: requires-python
Dynamic: summary
